{
  "$schema": "https://developer.microsoft.com/json-schemas/fabric/item/report/definition/bookmark/2.1.0/schema.json",
  "displayName": "Clear",
  "name": "Bookmarkff4045069ef7b9543e70",
  "options": {
    "applyOnlyToTargetVisuals": true,
    "targetVisualNames": [
      "d3a3e55c252d0687d5b4"
    ]
  },
  "explorationState": {
    "version": "1.3",
    "activeSection": "ReportSectionc2e9778dd899bccd64ca",
    "sections": {
      "ReportSectionc2e9778dd899bccd64ca": {
        "visualContainers": {
          "29ef56c05bba0b40cde3": {
            "filters": {
              "byExpr": [
                {
                  "name": "d9c4b4e9eb16b64e0257",
                  "type": "Categorical",
                  "expression": {
                    "Column": {
                      "Expression": {
                        "SourceRef": {
                          "Entity": "Cities"
                        }
                      },
                      "Property": "City"
                    }
                  },
                  "howCreated": 0
                },
                {
                  "name": "d6285c69f688ca53f0cb",
                  "type": "Advanced",
                  "expression": {
                    "Measure": {
                      "Expression": {
                        "SourceRef": {
                          "Entity": "Average Temperature by Month"
                        }
                      },
                      "Property": "Mean Temperature"
                    }
                  },
                  "howCreated": 0
                }
              ]
            },
            "singleVisual": {
              "visualType": "tableEx",
              "objects": {},
              "display": {
                "mode": "hidden"
              }
            }
          },
          "cad759179db0c7412ee7": {
            "singleVisual": {
              "visualType": "textbox",
              "objects": {}
            }
          },
          "abab9c6f1e5f3b5d9f68": {
            "singleVisual": {
              "visualType": "image",
              "objects": {}
            }
          },
          "4926a36f6d73074f4aed": {
            "singleVisual": {
              "visualType": "basicShape",
              "objects": {}
            }
          },
          "d3a3e55c252d0687d5b4": {
            "filters": {
              "byExpr": [
                {
                  "name": "1d8ca390050733d62224",
                  "type": "Categorical",
                  "expression": {
                    "Column": {
                      "Expression": {
                        "SourceRef": {
                          "Entity": "Cities"
                        }
                      },
                      "Property": "City"
                    }
                  },
                  "howCreated": 0
                },
                {
                  "name": "b1dc9f6be587cc62464c",
                  "type": "Advanced",
                  "expression": {
                    "Measure": {
                      "Expression": {
                        "SourceRef": {
                          "Entity": "Average Temperature by Month"
                        }
                      },
                      "Property": "Mean Temperature"
                    }
                  },
                  "howCreated": 0
                }
              ]
            },
            "singleVisual": {
              "visualType": "deneb7E15AEF80B9E4D4F8E12924291ECE89A",
              "objects": {}
            }
          },
          "794b70e8d2f00689c15c": {
            "filters": {
              "byExpr": [
                {
                  "name": "d9ce671e665d39ed78fe",
                  "type": "Advanced",
                  "expression": {
                    "Column": {
                      "Expression": {
                        "SourceRef": {
                          "Entity": "Date"
                        }
                      },
                      "Property": "Calendar Year"
                    }
                  },
                  "howCreated": 0
                },
                {
                  "name": "9690db2a70f71cb1b694",
                  "type": "Advanced",
                  "expression": {
                    "Measure": {
                      "Expression": {
                        "SourceRef": {
                          "Entity": "Average Temperature by Month"
                        }
                      },
                      "Property": "Mean Temperature"
                    }
                  },
                  "howCreated": 0
                },
                {
                  "name": "beb646a5e2df380bc5b0",
                  "type": "Advanced",
                  "expression": {
                    "Measure": {
                      "Expression": {
                        "SourceRef": {
                          "Entity": "Average Temperature by Month"
                        }
                      },
                      "Property": "10 Year Average by Month (C)"
                    }
                  },
                  "howCreated": 0
                }
              ]
            },
            "singleVisual": {
              "visualType": "lineChart",
              "objects": {},
              "activeProjections": {
                "Category": [
                  {
                    "Column": {
                      "Expression": {
                        "SourceRef": {
                          "Entity": "Date"
                        }
                      },
                      "Property": "Calendar Year"
                    }
                  }
                ]
              }
            }
          }
        }
      }
    },
    "objects": {
      "merge": {
        "outspacePane": [
          {
            "properties": {
              "expanded": {
                "expr": {
                  "Literal": {
                    "Value": "false"
                  }
                }
              }
            }
          }
        ]
      }
    }
  }
}